{
  "$schema": "https://json-schema.org/draft/2020-12/schema",
  "$id": "student-schedule.schema.json",
  "title": "Student Schedule Response",
  "type": "array",
  "items": {
    "type": "object",
    "required": [
      "classId",
      "className",
      "courseCode",
      "dayOfWeek",
      "startTime",
      "endTime",
      "location"
    ],
    "properties": {
      "classId": { "type": "integer" },
      "className": { "type": "string" },
      "courseCode": { "type": "string" },
      "dayOfWeek": { "type": "string", "enum": ["Mon", "Tue", "Wed", "Thu", "Fri"] },
      "startTime": { "type": "string", "pattern": "^\\d{2}:\\d{2}$" },
      "endTime": { "type": "string", "pattern": "^\\d{2}:\\d{2}$" },
      "location": { "type": "string" }
    }
  }
}
